pulumi_vault/__init__.py
pulumi_vault/_inputs.py
pulumi_vault/_utilities.py
pulumi_vault/audit.py
pulumi_vault/audit_request_header.py
pulumi_vault/auth_backend.py
pulumi_vault/cert_auth_backend_role.py
pulumi_vault/egp_policy.py
pulumi_vault/get_auth_backend.py
pulumi_vault/get_auth_backends.py
pulumi_vault/get_namespace.py
pulumi_vault/get_namespaces.py
pulumi_vault/get_nomad_access_token.py
pulumi_vault/get_policy_document.py
pulumi_vault/get_raft_autopilot_state.py
pulumi_vault/mfa_duo.py
pulumi_vault/mfa_okta.py
pulumi_vault/mfa_pingid.py
pulumi_vault/mfa_totp.py
pulumi_vault/mount.py
pulumi_vault/namespace.py
pulumi_vault/nomad_secret_backend.py
pulumi_vault/nomad_secret_role.py
pulumi_vault/oci_auth_backend.py
pulumi_vault/oci_auth_backend_role.py
pulumi_vault/outputs.py
pulumi_vault/plugin.py
pulumi_vault/plugin_pinned_version.py
pulumi_vault/policy.py
pulumi_vault/provider.py
pulumi_vault/pulumi-plugin.json
pulumi_vault/py.typed
pulumi_vault/quota_lease_count.py
pulumi_vault/quota_rate_limit.py
pulumi_vault/raft_autopilot.py
pulumi_vault/raft_snapshot_agent_config.py
pulumi_vault/rgp_policy.py
pulumi_vault/scep_auth_backend_role.py
pulumi_vault/token.py
pulumi_vault/ad/__init__.py
pulumi_vault/ad/get_access_credentials.py
pulumi_vault/ad/secret_backend.py
pulumi_vault/ad/secret_library.py
pulumi_vault/ad/secret_role.py
pulumi_vault/alicloud/__init__.py
pulumi_vault/alicloud/auth_backend_role.py
pulumi_vault/approle/__init__.py
pulumi_vault/approle/auth_backend_login.py
pulumi_vault/approle/auth_backend_role.py
pulumi_vault/approle/auth_backend_role_secret_id.py
pulumi_vault/approle/get_auth_backend_role_id.py
pulumi_vault/aws/__init__.py
pulumi_vault/aws/auth_backend_cert.py
pulumi_vault/aws/auth_backend_client.py
pulumi_vault/aws/auth_backend_config_identity.py
pulumi_vault/aws/auth_backend_identity_whitelist.py
pulumi_vault/aws/auth_backend_login.py
pulumi_vault/aws/auth_backend_role.py
pulumi_vault/aws/auth_backend_role_tag.py
pulumi_vault-7.4.1.dist-info/METADATA
pulumi_vault-7.4.1.dist-info/WHEEL
pulumi_vault-7.4.1.dist-info/top_level.txt
pulumi_vault-7.4.1.dist-info/RECORD
